MANIFEST.in
README.hmtl
README.rst
licence_en.txt
setup.py
version.txt
./fpylapack/fpylapack.pyf
./nnls_f77/nnls.f
./nnls_f77/nnls_f77.pyf
./nnls_f77/nnlsr.f
./nnls_f90/nnls.f90
fpylapack/__init__.py
fpylapack/fpylapack.pyf
nlsic/__init__.py
nlsic/lapack_ssg.py
nlsic/nlsic.py
nlsic/nnls.py
nlsic.egg-info/PKG-INFO
nlsic.egg-info/SOURCES.txt
nlsic.egg-info/dependency_links.txt
nlsic.egg-info/requires.txt
nlsic.egg-info/top_level.txt
nnls_f77/__init__.py
nnls_f77/nnls.f
nnls_f77/nnls_f77.pyf
nnls_f77/nnlsr.f
nnls_f90/__init__.py
nnls_f90/nnls.f90