Metadata-Version: 2.1
Name: nlsic
Version: 1.3.4
Summary: Non-linear Least Squares with Inequality Constraints
Home-page: https://github.com/sgsokol/nlsic_py/
Author: Serguei Sokol
Author-email: sokol@insa-toulouse.fr
License: GNU General Public License v2 or later (GPLv2+)
Keywords: least squares
Platform: UNKNOWN
